{
	"mechDataAssetId":
	{
		"id": "MWMechDataAsset:PNT-8Z_MDA"
	},
	"customName": "",
	"skinCustomization":
	{
		"mechSkinAssetId":
		{
			"id": "MWUnitSkinAsset:Panther_Default_SKN"
		},
		"customMechSkinId": "None",
		"bPrimaryColorSet": true,
		"primaryColor":
		{
			"r": 0.064803265035152435,
			"g": 0.16202940046787262,
			"b": 0.21223078668117523,
			"a": 1
		},
		"bSecondaryColorSet": true,
		"secondaryColor":
		{
			"r": 0.020289000123739243,
			"g": 0.038203999400138855,
			"b": 0.074213996529579163,
			"a": 1
		},
		"bTertiaryColorSet": true,
		"tertiaryColor":
		{
			"r": 0.057805001735687256,
			"g": 0.63075697422027588,
			"b": 0.78353798389434814,
			"a": 1
		}
	},
	"currentStructure":
	{
		"head": 15,
		"centerTorso": 22,
		"leftTorso": 16,
		"rightTorso": 16,
		"leftArm": 12,
		"rightArm": 12,
		"leftLeg": 16,
		"rightLeg": 16
	},
	"currentArmor":
	{
		"head": 20,
		"centerTorso": 32,
		"leftTorso": 24,
		"rightTorso": 24,
		"leftArm": 24,
		"rightArm": 24,
		"leftLeg": 32,
		"rightLeg": 32
	},
	"currentRearArmor":
	{
		"centerTorsoRear": 12,
		"leftTorsoRear": 8,
		"rightTorsoRear": 8
	},
	"installedArmor":
	{
		"head": 20,
		"centerTorso": 32,
		"leftTorso": 24,
		"rightTorso": 24,
		"leftArm": 24,
		"rightArm": 24,
		"leftLeg": 32,
		"rightLeg": 32
	},
	"installedRearArmor":
	{
		"centerTorsoRear": 12,
		"leftTorsoRear": 8,
		"rightTorsoRear": 8
	},
	"installedWeapons": [
		{
			"hardpointSlotId": "Torso_Center_MH1_srm4",
			"weaponData":
			{
				"weaponId":
				{
					"id": "MWMissileWeaponDataAsset:Srm4"
				},
				"healthState": "Healthy"
			}
		},
		{
			"hardpointSlotId": "Forearm_Right_EH1_largelaser",
			"weaponData":
			{
				"weaponId":
				{
					"id": "MWTraceWeaponDataAsset:Largelaser"
				},
				"healthState": "Healthy"
			}
		},
		{
			"hardpointSlotId": "Arm_Left_Hand_Actuator_Melee",
			"weaponData":
			{
				"weaponId":
				{
					"id": ""
				},
				"healthState": "Healthy"
			}
		},
		{
			"hardpointSlotId": "Arm_Right_Hand_Actuator_Melee",
			"weaponData":
			{
				"weaponId":
				{
					"id": ""
				},
				"healthState": "Healthy"
			}
		}
	],
	"weaponGroupInfo":
	{
		"weaponGroups": [
			{
				"hardpointSlotId": "Torso_Center_MH1_srm4",
				"bWeaponGroup1": false,
				"bWeaponGroup2": true,
				"bWeaponGroup3": false,
				"bWeaponGroup4": false,
				"bWeaponGroup5": false,
				"bWeaponGroup6": false
			},
			{
				"hardpointSlotId": "Forearm_Right_EH1_largelaser",
				"bWeaponGroup1": true,
				"bWeaponGroup2": false,
				"bWeaponGroup3": false,
				"bWeaponGroup4": false,
				"bWeaponGroup5": false,
				"bWeaponGroup6": false
			},
			{
				"hardpointSlotId": "Arm_Left_Hand_Actuator_Melee",
				"bWeaponGroup1": false,
				"bWeaponGroup2": false,
				"bWeaponGroup3": false,
				"bWeaponGroup4": false,
				"bWeaponGroup5": true,
				"bWeaponGroup6": false
			},
			{
				"hardpointSlotId": "Arm_Right_Hand_Actuator_Melee",
				"bWeaponGroup1": false,
				"bWeaponGroup2": false,
				"bWeaponGroup3": false,
				"bWeaponGroup4": false,
				"bWeaponGroup5": true,
				"bWeaponGroup6": false
			}
		],
		"chainFireGroups": []
	},
	"equipment":
	{
		"mechPartEquipment": [
			{
				"mechPart": "Head",
				"slottedEquipment": [
					{
						"slotId": 0,
						"slotTypeAssetId":
						{
							"id": "MWSlotTypeDataAsset:General_SlotType"
						},
						"equipmentData":
						{
							"equipmentId":
							{
								"id": "MWHeatSinkDataAsset:SingleHeatSink"
							},
							"healthState": "Healthy"
						}
					}
				]
			},
			{
				"mechPart": "LeftTorso",
				"slottedEquipment": [
					{
						"slotId": 0,
						"slotTypeAssetId":
						{
							"id": "MWSlotTypeDataAsset:General_SlotType"
						},
						"equipmentData":
						{
							"equipmentId":
							{
								"id": "MWHeatSinkDataAsset:SingleHeatSink"
							},
							"healthState": "Healthy"
						}
					},
					{
						"slotId": 1,
						"slotTypeAssetId":
						{
							"id": "MWSlotTypeDataAsset:General_SlotType"
						},
						"equipmentData":
						{
							"equipmentId":
							{
								"id": "MWHeatSinkDataAsset:SingleHeatSink"
							},
							"healthState": "Healthy"
						}
					},
					{
						"slotId": 2,
						"slotTypeAssetId":
						{
							"id": "MWSlotTypeDataAsset:General_SlotType"
						},
						"equipmentData":
						{
							"equipmentId":
							{
								"id": "MWHeatSinkDataAsset:SingleHeatSink"
							},
							"healthState": "Healthy"
						}
					},
					{
						"slotId": 3,
						"slotTypeAssetId":
						{
							"id": "MWSlotTypeDataAsset:General_SlotType"
						},
						"equipmentData":
						{
							"equipmentId":
							{
								"id": "MWHeatSinkDataAsset:SingleHeatSink"
							},
							"healthState": "Healthy"
						}
					},
					{
						"slotId": 4,
						"slotTypeAssetId":
						{
							"id": "MWSlotTypeDataAsset:General_SlotType"
						},
						"equipmentData":
						{
							"equipmentId":
							{
								"id": "MWAmmoDataAsset:Srm_AmmoEquipment"
							},
							"healthState": "Healthy"
						}
					}
				]
			},
			{
				"mechPart": "RightTorso",
				"slottedEquipment": [
					{
						"slotId": 0,
						"slotTypeAssetId":
						{
							"id": "MWSlotTypeDataAsset:General_SlotType"
						},
						"equipmentData":
						{
							"equipmentId":
							{
								"id": "MWHeatSinkDataAsset:SingleHeatSink"
							},
							"healthState": "Healthy"
						}
					},
					{
						"slotId": 1,
						"slotTypeAssetId":
						{
							"id": "MWSlotTypeDataAsset:General_SlotType"
						},
						"equipmentData":
						{
							"equipmentId":
							{
								"id": "MWHeatSinkDataAsset:SingleHeatSink"
							},
							"healthState": "Healthy"
						}
					},
					{
						"slotId": 2,
						"slotTypeAssetId":
						{
							"id": "MWSlotTypeDataAsset:General_SlotType"
						},
						"equipmentData":
						{
							"equipmentId":
							{
								"id": "MWHeatSinkDataAsset:SingleHeatSink"
							},
							"healthState": "Healthy"
						}
					},
					{
						"slotId": 3,
						"slotTypeAssetId":
						{
							"id": "MWSlotTypeDataAsset:General_SlotType"
						},
						"equipmentData":
						{
							"equipmentId":
							{
								"id": "MWHeatSinkDataAsset:SingleHeatSink"
							},
							"healthState": "Healthy"
						}
					}
				]
			},
			{
				"mechPart": "LeftLeg",
				"slottedEquipment": [
					{
						"slotId": 0,
						"slotTypeAssetId":
						{
							"id": "MWSlotTypeDataAsset:JumpJetClass5_SlotType"
						},
						"equipmentData":
						{
							"equipmentId":
							{
								"id": "MWJumpJetDataAsset:JumpJet_Class5_Equipment"
							},
							"healthState": "Healthy"
						}
					},
					{
						"slotId": 1,
						"slotTypeAssetId":
						{
							"id": "MWSlotTypeDataAsset:JumpJetClass5_SlotType"
						},
						"equipmentData":
						{
							"equipmentId":
							{
								"id": "MWJumpJetDataAsset:JumpJet_Class5_Equipment"
							},
							"healthState": "Healthy"
						}
					}
				]
			},
			{
				"mechPart": "RightLeg",
				"slottedEquipment": [
					{
						"slotId": 0,
						"slotTypeAssetId":
						{
							"id": "MWSlotTypeDataAsset:JumpJetClass5_SlotType"
						},
						"equipmentData":
						{
							"equipmentId":
							{
								"id": "MWJumpJetDataAsset:JumpJet_Class5_Equipment"
							},
							"healthState": "Healthy"
						}
					},
					{
						"slotId": 1,
						"slotTypeAssetId":
						{
							"id": "MWSlotTypeDataAsset:JumpJetClass5_SlotType"
						},
						"equipmentData":
						{
							"equipmentId":
							{
								"id": "MWJumpJetDataAsset:JumpJet_Class5_Equipment"
							},
							"healthState": "Healthy"
						}
					}
				]
			}
		]
	},
	"installedTraits": []
}