{
	"mechModel": "MWMechModelDataAsset'/Game/Objects/Mechs/Quickdraw/Model/Quickdraw_MDL.Quickdraw_MDL'",
	"bReadFromFileOnSave": true,
	"mechStats":
	{
		"keyName": "QKD-IV4",
		"table": "DataTable'/Game/Objects/Mechs/_common/Config/MechStats.MechStats'"
	},
	"healthStats":
	{
		"keyName": "QKD-IV4",
		"table": "DataTable'/Game/Objects/Mechs/_common/Config/MechHealthStats.MechHealthStats'"
	},
	"mechDataStats":
	{
		"baseStats":
		{
			"tons": 60,
			"baseTons": 17,
			"cBillBaseValue": 10000,
			"cBillUpkeepCost": 50000,
			"repairData":
			{
				"costPerArmorPoint": 200,
				"costPerStructurePoint": 400,
				"partReplacementCost":
				{
					"head": 370000,
					"centerTorso": 1152000,
					"sideTorso": 120000,
					"arm": 15000,
					"leg": 21000
				}
			},
			"refitCosts":
			{
				"id": ""
			},
			"baseHeatCapacity": 39.599998474121094,
			"baseCoolingRate": 0.95999997854232788
		},
		"moveStats":
		{
			"topSpeed": 1800,
			"minSpeed": 400,
			"reverseTopSpeed": 1198.800048828125,
			"accelerationCurve": "CurveFloat'/Game/Objects/Mechs/_common/Config/MechDefaultAcceleration.MechDefaultAcceleration'",
			"decelerationCurve": "CurveFloat'/Game/Objects/Mechs/_common/Config/MechDefaultDeceleration.MechDefaultDeceleration'",
			"slowFieldDecelerationCurve": "CurveFloat'/Game/Objects/Mechs/_common/Config/MechSlowFieldDeceleration.MechSlowFieldDeceleration'",
			"turnSpeedCurve": "CurveFloat'/Game/Objects/Mechs/_common/Config/MechDefaultTurnSpeed.MechDefaultTurnSpeed'",
			"turnSpeed": 107.71610260009766,
			"jumpJetCrouchCurve": "CurveFloat'/Game/Objects/Mechs/_common/Config/MechJumpJetLeap.MechJumpJetLeap'",
			"jumpJetLandingRecoveryCurve": "None",
			"fallDamageCurve": "CurveFloat'/Game/Objects/Mechs/_common/Config/MechFallDamageCurve.MechFallDamageCurve'"
		},
		"torsoStats":
		{
			"torsoTwistRate":
			{
				"yaw": 135,
				"pitch": 84.379997253417969
			},
			"torsoTwistBounds":
			{
				"bIsYawUnbound": false,
				"bIsPitchUnbound": false,
				"low":
				{
					"yaw": -100,
					"pitch": -35
				},
				"high":
				{
					"yaw": 100,
					"pitch": 35
				}
			},
			"armTwistRate":
			{
				"yaw": 337.5,
				"pitch": 337.5
			},
			"armTwistBounds":
			{
				"bIsYawUnbound": false,
				"bIsPitchUnbound": false,
				"low":
				{
					"yaw": -35,
					"pitch": -40
				},
				"high":
				{
					"yaw": 35,
					"pitch": 40
				}
			}
		},
		"powerStats":
		{
			"powerInitializationTime": 8,
			"powerUpTime": 3,
			"powerDownTime": 3,
			"torsoPowerUpCurve": "CurveFloat'/Game/Objects/Mechs/_common/Config/MechDefaultPowerAnimatonCurves/MechDefaultTorsoPowerUp.MechDefaultTorsoPowerUp'",
			"torsoPowerDownCurve": "CurveFloat'/Game/Objects/Mechs/_common/Config/MechDefaultPowerAnimatonCurves/MechDefaultTorsoPowerDown.MechDefaultTorsoPowerDown'",
			"armPowerUpCurve": "CurveFloat'/Game/Objects/Mechs/_common/Config/MechDefaultPowerAnimatonCurves/MechDefaultArmPowerUp.MechDefaultArmPowerUp'",
			"armPowerDownCurve": "CurveFloat'/Game/Objects/Mechs/_common/Config/MechDefaultPowerAnimatonCurves/MechDefaultArmPowerDown.MechDefaultArmPowerDown'",
			"legPowerUpCurve": "CurveFloat'/Game/Objects/Mechs/_common/Config/MechDefaultPowerAnimatonCurves/MechDefaultLegPowerUp.MechDefaultLegPowerUp'",
			"legPowerDownCurve": "CurveFloat'/Game/Objects/Mechs/_common/Config/MechDefaultPowerAnimatonCurves/MechDefaultLegPowerDown.MechDefaultLegPowerDown'"
		},
		"mechImportData":
		{
			"baseMechInformation":
			{
				"armorType": "ferrofibrousarmortype",
				"structureType": "standardstructuretype",
				"heatSinkType": "doubleheatsinktype",
				"bArtemis": false,
				"engineRating": 240,
				"bXLEngine": true
			},
			"componentInformation":
			{
				"head":
				{
					"bCASE": false,
					"targetingComputer": 0,
					"bECM": false,
					"bBeagleActiveProbe": false,
					"heatSinks": 0,
					"componentAmmo": [],
					"jumpJets": 0
				},
				"centerTorso":
				{
					"bCASE": false,
					"targetingComputer": 0,
					"bECM": false,
					"bBeagleActiveProbe": false,
					"heatSinks": 0,
					"componentAmmo": [],
					"jumpJets": 0
				},
				"leftTorso":
				{
					"bCASE": false,
					"targetingComputer": 0,
					"bECM": false,
					"bBeagleActiveProbe": false,
					"heatSinks": 1,
					"componentAmmo": [
						"/Game/Objects/Weapons/_common/AmmoEquipment/AC5_Standard_AmmoEquipment.AC5_Standard_AmmoEquipment",
						"/Game/Objects/Weapons/_common/AmmoEquipment/SRM_AmmoEquipment.SRM_AmmoEquipment"
					],
					"jumpJets": 1
				},
				"rightTorso":
				{
					"bCASE": false,
					"targetingComputer": 0,
					"bECM": false,
					"bBeagleActiveProbe": false,
					"heatSinks": 1,
					"componentAmmo": [
						"/Game/Objects/Weapons/_common/AmmoEquipment/AC5_Standard_AmmoEquipment.AC5_Standard_AmmoEquipment",
						"/Game/Objects/Weapons/_common/AmmoEquipment/SRM_AmmoEquipment.SRM_AmmoEquipment"
					],
					"jumpJets": 1
				},
				"leftArm":
				{
					"bCASE": false,
					"targetingComputer": 0,
					"bECM": false,
					"bBeagleActiveProbe": false,
					"heatSinks": 0,
					"componentAmmo": [],
					"jumpJets": 0
				},
				"rightArm":
				{
					"bCASE": false,
					"targetingComputer": 0,
					"bECM": false,
					"bBeagleActiveProbe": false,
					"heatSinks": 0,
					"componentAmmo": [],
					"jumpJets": 0
				},
				"leftLeg":
				{
					"bCASE": false,
					"targetingComputer": 0,
					"bECM": false,
					"bBeagleActiveProbe": false,
					"heatSinks": 0,
					"componentAmmo": [],
					"jumpJets": 0
				},
				"rightLeg":
				{
					"bCASE": false,
					"targetingComputer": 0,
					"bECM": false,
					"bBeagleActiveProbe": false,
					"heatSinks": 0,
					"componentAmmo": [],
					"jumpJets": 0
				}
			}
		}
	},
	"healthDataStats":
	{
		"maxStructure":
		{
			"head": 15,
			"centerTorso": 40,
			"leftTorso": 28,
			"rightTorso": 28,
			"leftArm": 20,
			"rightArm": 20,
			"leftLeg": 28,
			"rightLeg": 28
		},
		"maxArmor":
		{
			"head": 30,
			"centerTorso": 80,
			"leftTorso": 56,
			"rightTorso": 56,
			"leftArm": 40,
			"rightArm": 40,
			"leftLeg": 56,
			"rightLeg": 56
		}
	},
	"mechType":
	{
		"tagName": "Mech.Heavy.Quickdraw.QKD-IV4"
	},
	"chassisFullName": "Quickdraw",
	"variantName": "QKD-IV4",
	"defaultMech":
	{
		"id": "MWMechLoadoutAsset:QKD-IV4_Loadout"
	},
	"mechTexture": "/Game/UI/Textures/Battlemechs/Quickdraw_Icon_UIX.Quickdraw_Icon_UIX",
	"targetComponent": "/Game/Objects/Mechs/Quickdraw/Target/Quickdraw_Target.Quickdraw_Target_C",
	"description": "Ivy Upsalom leads Upsalom's Support Lance, a unit of Redjack Ryan's pirate 'Mech force. Known to monitor enemy tactical frequencies in the hopes of discerning any female MechWarriors and challenging them to personal combat in her Quickdraw. Her claim to the best woman MechWarrior in the Inner Sphere is still undisputed as Upsalom's 30 combat kills attest, also earning her the moniker 'Ladykiller'.",
	"selectedWeaponHardPoints": [
		"Torso_Left_MH1_srm6",
		"Torso_Center_EH1_mediumpulselaser",
		"Torso_Center_EH2_mediumpulselaser",
		"Torso_Right_MH1_srm6",
		"Forearm_Right_BH1_autocannon5",
		"Forearm_Left_BH1_autocannon5",
		"Arm_Left_Hand_Actuator_Melee",
		"Arm_Right_Hand_Actuator_Melee"
	],
	"blankWeaponHardPoints": [
		"Torso_Center_EH1_blank"
	],
	"bRecalculateFreeSlotsOnSave": true,
	"equipmentAllocation":
	{
		"armorDataAssetId":
		{
			"id": "MWArmorDataAsset:FerroFibrousArmor"
		},
		"structureDataAssetId":
		{
			"id": "MWStructureDataAsset:StandardStructure"
		},
		"allowedHeatSinkType":
		{
			"tagName": "Equipment.HeatSinks.Double"
		},
		"allowedJumpJetType":
		{
			"tagName": "Equipment.JumpJets.Class3"
		},
		"slotData": [
			{
				"slotTypeDataAssetId":
				{
					"id": "MWSlotTypeDataAsset:General_SlotType"
				},
				"slotCounts":
				{
					"Head": 1,
					"CenterTorso": 0,
					"LeftTorso": 6,
					"LeftArm": 4,
					"LeftLeg": 2,
					"RightTorso": 6,
					"RightArm": 4,
					"RightLeg": 2
				}
			},
			{
				"slotTypeDataAssetId":
				{
					"id": "MWSlotTypeDataAsset:JumpJetClass3_SlotType"
				},
				"slotCounts":
				{
					"Head": 0,
					"CenterTorso": 0,
					"LeftTorso": 1,
					"RightTorso": 1,
					"LeftArm": 0,
					"RightArm": 0,
					"LeftLeg": 0,
					"RightLeg": 0
				}
			}
		],
		"internalEquipment": [
			"LifeSupport",
			"Sensors",
			"Cockpit",
			"Gyro",
			"LeftArm_Shoulder",
			"LeftArm_UpperActuator",
			"RightArm_Shoulder",
			"RightArm_UpperActuator",
			"LeftLeg_Hip",
			"LeftLeg_UpperActuator",
			"LeftLeg_LowerActuator",
			"LeftLeg_FootActuator",
			"RightLeg_Hip",
			"RightLeg_UpperActuator",
			"RightLeg_LowerActuator",
			"RightLeg_FootActuator"
		],
		"totalTraitSlots": 9
	},
	"refitCosts":
	{
		"id": "MWMechRefitCostsDataAsset:QKD_240_XL_RefitCosts"
	},
	"engineRating": 240,
	"bXLEngine": true,
	"baseChassisCost": 8579200,
	"salvageShareCost": 30,
	"bIsHeroMech": true,
	"bIsDefaultVariant": false
}